.editorconfig
.travis.yml
AUTHORS
CONTRIBUTING.rst
ChangeLog
LICENSE
README.rst
VERSION
requirements.txt
setup.cfg
setup.py
test-requirements.txt
tox.ini
sphinxcontrib/__init__.py
sphinxcontrib/gravizo/__init__.py
sphinxcontrib/gravizo/gravizo.py
sphinxcontrib_gravizo.egg-info/PKG-INFO
sphinxcontrib_gravizo.egg-info/SOURCES.txt
sphinxcontrib_gravizo.egg-info/dependency_links.txt
sphinxcontrib_gravizo.egg-info/namespace_packages.txt
sphinxcontrib_gravizo.egg-info/not-zip-safe
sphinxcontrib_gravizo.egg-info/pbr.json
sphinxcontrib_gravizo.egg-info/requires.txt
sphinxcontrib_gravizo.egg-info/top_level.txt
tests/conftest.py
tests/test_stub.py